Metadata-Version: 2.1
Name: elixir-nbc
Version: 7.1.0.dev0
Summary: Converting Elixir Notebooks
Project-URL: Homepage, https://ciusji.gitbook.io/elixirnote/guides/elixirnote-nbc
Author-email: ciusji <bqjimaster@gmail.com>
License: # Licensing terms
License-File: LICENSE
Keywords: Interactive,Interpreter,Shell,Web
Classifier: Intended Audience :: Developers
Classifier: Intended Audience :: Science/Research
Classifier: Intended Audience :: System Administrators
Classifier: License :: OSI Approved :: BSD License
Classifier: Programming Language :: Python
Classifier: Programming Language :: Python :: 3
Requires-Python: >=3.7
Requires-Dist: beautifulsoup4
Requires-Dist: bleach
Requires-Dist: defusedxml
Requires-Dist: importlib-metadata>=3.6; python_version < '3.10'
Requires-Dist: jinja2>=3.0
Requires-Dist: jupyter-core>=4.7
Requires-Dist: jupyterlab-pygments
Requires-Dist: markupsafe>=2.0
Requires-Dist: mistune<3,>=2.0.3
Requires-Dist: nbclient>=0.5.0
Requires-Dist: nbformat>=5.1
Requires-Dist: packaging
Requires-Dist: pandocfilters>=1.4.1
Requires-Dist: pygments>=2.4.1
Requires-Dist: tinycss2
Requires-Dist: traitlets>=5.0
Provides-Extra: all
Requires-Dist: ipykernel; extra == 'all'
Requires-Dist: ipython; extra == 'all'
Requires-Dist: ipywidgets>=7; extra == 'all'
Requires-Dist: nbsphinx>=0.2.12; extra == 'all'
Requires-Dist: pre-commit; extra == 'all'
Requires-Dist: pyppeteer<1.1,>=1; extra == 'all'
Requires-Dist: pyqtwebengine>=5.15; extra == 'all'
Requires-Dist: pytest; extra == 'all'
Requires-Dist: pytest-cov; extra == 'all'
Requires-Dist: pytest-dependency; extra == 'all'
Requires-Dist: sphinx-rtd-theme; extra == 'all'
Requires-Dist: sphinx==5.0.2; extra == 'all'
Requires-Dist: tornado>=6.1; extra == 'all'
Provides-Extra: docs
Requires-Dist: ipython; extra == 'docs'
Requires-Dist: nbsphinx>=0.2.12; extra == 'docs'
Requires-Dist: sphinx-rtd-theme; extra == 'docs'
Requires-Dist: sphinx==5.0.2; extra == 'docs'
Provides-Extra: qtpdf
Requires-Dist: pyqtwebengine>=5.15; extra == 'qtpdf'
Provides-Extra: qtpng
Requires-Dist: pyqtwebengine>=5.15; extra == 'qtpng'
Provides-Extra: serve
Requires-Dist: tornado>=6.1; extra == 'serve'
Provides-Extra: test
Requires-Dist: ipykernel; extra == 'test'
Requires-Dist: ipywidgets>=7; extra == 'test'
Requires-Dist: pre-commit; extra == 'test'
Requires-Dist: pyppeteer<1.1,>=1; extra == 'test'
Requires-Dist: pytest; extra == 'test'
Requires-Dist: pytest-cov; extra == 'test'
Requires-Dist: pytest-dependency; extra == 'test'
Provides-Extra: webpdf
Requires-Dist: pyppeteer<1.1,>=1; extra == 'webpdf'
